pyqtribbon/__init__.py
pyqtribbon/_version.py
pyqtribbon/category.py
pyqtribbon/constants.py
pyqtribbon/gallery.py
pyqtribbon/logger.py
pyqtribbon/menu.py
pyqtribbon/panel.py
pyqtribbon/panel.pyi
pyqtribbon/ribbonbar.py
pyqtribbon/screenshotwindow.py
pyqtribbon/separator.py
pyqtribbon/tabbar.py
pyqtribbon/titlewidget.py
pyqtribbon/toolbutton.py
pyqtribbon/utils.py
pyqtribbon/version.py
pyqtribbon/icons/backward.png
pyqtribbon/icons/close.png
pyqtribbon/icons/down.png
pyqtribbon/icons/forward.png
pyqtribbon/icons/help.png
pyqtribbon/icons/linking.png
pyqtribbon/icons/max.png
pyqtribbon/icons/min.png
pyqtribbon/icons/more.png
pyqtribbon/icons/python.png
pyqtribbon/icons/redo.png
pyqtribbon/icons/save.png
pyqtribbon/icons/undo.png
pyqtribbon/icons/up.png
pyqtribbon/styles/base.qss
pyqtribbon/styles/debug.qss
pyqtribbon/styles/default.qss
pyqtribbon-0.7.8.dist-info/licenses/LICENSE
pyqtribbon-0.7.8.dist-info/METADATA
pyqtribbon-0.7.8.dist-info/WHEEL
pyqtribbon-0.7.8.dist-info/top_level.txt
pyqtribbon-0.7.8.dist-info/RECORD
