Metadata-Version: 2.4
Name: pyqtribbon
Version: 0.7.8
Summary: Ribbon Bar for PyQt or PySide applications
Author-email: WANG Hailin <hailin.wang@connect.polyu.hk>
Project-URL: GitHub, https://github.com/haiiliin/pyqtribbon
Project-URL: Documentation, https://pyqribbon.readthedocs.io/en/stable/
Classifier: Programming Language :: Python
Classifier: Programming Language :: Python :: 3
Classifier: Programming Language :: Python :: 3.8
Classifier: Programming Language :: Python :: 3.9
Classifier: Programming Language :: Python :: 3.10
Classifier: Programming Language :: Python :: 3.11
Classifier: Programming Language :: Python :: 3.12
Classifier: Programming Language :: Python :: 3.13
Classifier: License :: OSI Approved :: MIT License
Classifier: Operating System :: OS Independent
Classifier: Development Status :: 4 - Beta
Requires-Python: >=3.8
License-File: LICENSE
Requires-Dist: numpy
Requires-Dist: qtpy
Dynamic: license-file
